swa_cc/__init__.py
swa_cc/secure_s3_storage_bucket.py
swa_cc/secure_s3_storage_bucket/__init__.py
swa_cc.secure_s3_storage_bucket-1.3.0.dist-info/METADATA
swa_cc.secure_s3_storage_bucket-1.3.0.dist-info/WHEEL
swa_cc.secure_s3_storage_bucket-1.3.0.dist-info/top_level.txt
swa_cc.secure_s3_storage_bucket-1.3.0.dist-info/RECORD
