Metadata-Version: 2.1
Name: swa-cc.secure-s3-storage-bucket
Version: 1.3.0
Summary: A CDK stack for creating a swa approved s3 bucket
Home-page: UNKNOWN
Author: Seth Dobson
Author-email: sd0408@gmail.com
License: UNKNOWN
Platform: UNKNOWN
Classifier: Development Status :: 4 - Beta
Classifier: Intended Audience :: Developers
Classifier: License :: OSI Approved :: Apache Software License
Classifier: Programming Language :: JavaScript
Classifier: Programming Language :: Python :: 3 :: Only
Classifier: Programming Language :: Python :: 3.6
Classifier: Programming Language :: Python :: 3.7
Classifier: Programming Language :: Python :: 3.8
Classifier: Topic :: Software Development :: Code Generators
Classifier: Topic :: Utilities
Classifier: Typing :: Typed
Requires-Python: >=3.6
Requires-Dist: aws-cdk.core
Requires-Dist: aws-cdk.aws-s3
Requires-Dist: aws-cdk.aws-kms
Requires-Dist: aws-cdk.aws-iam
Requires-Dist: aws-cdk.aws-events
Requires-Dist: swa-cc.core
